src/__init__.py
src/core.py
src/test_core.py
mkdocs_techdocs_core_alexef-1.4.0.dist-info/LICENSE
mkdocs_techdocs_core_alexef-1.4.0.dist-info/METADATA
mkdocs_techdocs_core_alexef-1.4.0.dist-info/WHEEL
mkdocs_techdocs_core_alexef-1.4.0.dist-info/entry_points.txt
mkdocs_techdocs_core_alexef-1.4.0.dist-info/top_level.txt
mkdocs_techdocs_core_alexef-1.4.0.dist-info/RECORD
