Metadata-Version: 2.1
Name: mkdocs-techdocs-core-alexef
Version: 1.4.0
Summary: The core MkDocs plugin used by Backstage's TechDocs as a wrapper around multiple MkDocs plugins and Python Markdown extensions
Home-page: https://github.com/backstage/mkdocs-techdocs-core
Author: TechDocs Core
Author-email: pulp-fiction@spotify.com
License: Apache-2.0
Keywords: mkdocs
Classifier: Development Status :: 3 - Alpha
Classifier: Intended Audience :: Developers
Classifier: Intended Audience :: Information Technology
Classifier: License :: OSI Approved :: Apache Software License
Classifier: Programming Language :: Python
Classifier: Programming Language :: Python :: 3 :: Only
Classifier: Programming Language :: Python :: 3.8
Requires-Python: >=3.7
License-File: LICENSE
Requires-Dist: mkdocs >=1.6
Requires-Dist: Markdown <3.4,>=3.2
Requires-Dist: mkdocs-material ==9.5.27
Requires-Dist: markdown-inline-graphviz-extension ==1.1.2
Requires-Dist: mkdocs-monorepo-plugin ==1.1.0
Requires-Dist: plantuml-markdown ==3.9.7
Requires-Dist: mdx-truly-sane-lists ==1.3
Requires-Dist: pymdown-extensions ==10.3.1
Requires-Dist: pygments ==2.17.2
